MANIFEST.in
README.rst
VERSION
requirements.txt
setup.cfg
setup.py
test-requirements.txt
tests/__init__.py
tests/api/__init__.py
tests/api/other/__init__.py
tests/api/other/audit_test.py
tests/util/__init__.py
tests/util/common_test.py
tests/util/token_request_test.py
viperpy/__init__.py
viperpy.egg-info/PKG-INFO
viperpy.egg-info/SOURCES.txt
viperpy.egg-info/dependency_links.txt
viperpy.egg-info/not-zip-safe
viperpy.egg-info/requires.txt
viperpy.egg-info/top_level.txt
viperpy/api/__init__.py
viperpy/api/authentication.py
viperpy/api/license.py
viperpy/api/block/__init__.py
viperpy/api/block/volumes.py
viperpy/api/block/vpools.py
viperpy/api/compute/__init__.py
viperpy/api/compute/vcenters.py
viperpy/api/fabric/__init__.py
viperpy/api/fabric/capacity.py
viperpy/api/fabric/disk.py
viperpy/api/fabric/health.py
viperpy/api/fabric/node.py
viperpy/api/fabric/services.py
viperpy/api/object_data_control/__init__.py
viperpy/api/object_data_control/billing.py
viperpy/api/object_data_control/bucket.py
viperpy/api/object_data_control/capacity_info.py
viperpy/api/object_data_control/namespace.py
viperpy/api/object_data_control/object_soft_quota.py
viperpy/api/object_data_control/user_mangement.py
viperpy/api/object_data_control/user_secret_key.py
viperpy/api/other/__init__.py
viperpy/api/other/audit.py
viperpy/api/other/user_info.py
viperpy/api/system_management/__init__.py
viperpy/api/system_management/configuration.py
viperpy/api/system_management/health_monitor.py
viperpy/api/system_management/upgrade.py
viperpy/api/tenant/__init__.py
viperpy/api/tenant/projects.py
viperpy/api/tenant/tenants.py
viperpy/util/__init__.py
viperpy/util/common.py
viperpy/util/exceptions.py
viperpy/util/token_request.py