Metadata-Version: 1.0
Name: viperpy
Version: 0.8.3
Summary: A library for interacting with the EMC ViPR API
Home-page: https://github.com/chadlung/viperpy
Author: Chad Lung, EMC Rubicon
Author-email: chad.lung@gmail.com
License: UNKNOWN
Keywords: vipr
Platform: UNKNOWN
